dictrack/__init__.py
dictrack/events.py
dictrack/manager.py
dictrack/conditions/__init__.py
dictrack/conditions/base.py
dictrack/conditions/keys.py
dictrack/data_caches/__init__.py
dictrack/data_caches/base.py
dictrack/data_caches/memory.py
dictrack/data_caches/redis.py
dictrack/data_stores/__init__.py
dictrack/data_stores/base.py
dictrack/data_stores/mongodb.py
dictrack/limiters/__init__.py
dictrack/limiters/base.py
dictrack/limiters/count.py
dictrack/limiters/time.py
dictrack/trackers/__init__.py
dictrack/trackers/base.py
dictrack/trackers/numerics/__init__.py
dictrack/trackers/numerics/accumulation.py
dictrack/trackers/numerics/count.py
dictrack/trackers/numerics/numeric.py
dictrack/utils/__init__.py
dictrack/utils/errors.py
dictrack/utils/logger.py
dictrack/utils/utils.py
dictrack-2.1.5.dist-info/LICENSE
dictrack-2.1.5.dist-info/METADATA
dictrack-2.1.5.dist-info/WHEEL
dictrack-2.1.5.dist-info/top_level.txt
dictrack-2.1.5.dist-info/RECORD
